LICENSE
MANIFEST.in
README.rst
build_docs.sh
requirements.txt
setup.py
django_stories.egg-info/PKG-INFO
django_stories.egg-info/SOURCES.txt
django_stories.egg-info/dependency_links.txt
django_stories.egg-info/requires.txt
django_stories.egg-info/top_level.txt
doc_src/author_guide.rst
doc_src/index.rst
doc_src/install.rst
doc_src/pagination.rst
doc_src/settings.rst
doc_src/upgrading.rst
doc_src/_static/breadcrumb_background.png
doc_src/_static/default.css
doc_src/_static/documentation.png
doc_src/_static/header_sm_mid.png
doc_src/_static/scrn1.png
doc_src/_static/scrn2.png
doc_src/_static/searchfield_leftcap.png
doc_src/_static/searchfield_repeat.png
doc_src/_static/searchfield_rightcap.png
doc_src/_static/title_background.png
doc_src/_static/toc.js
doc_src/_static/triangle_closed.png
doc_src/_static/triangle_left.png
doc_src/_static/triangle_open.png
doc_src/_templates/layout.html
doc_src/integration/categories_integration.rst
doc_src/integration/index.rst
doc_src/integration/reversion_integration.rst
doc_src/integration/tinymce_integration.rst
doc_src/reference/index.rst
doc_src/reference/models.rst
doc_src/reference/paginator.rst
doc_src/reference/templatetags.rst
doc_src/reference/urls.rst
doc_src/reference/views.rst
doc_src/user/index.rst
doc_src/user/revisions.rst
doc_src/user/storyentry.rst
doc_src/user/images/history_btn.png
doc_src/user/images/history_list.png
doc_src/user/images/history_save_btn.png
doc_src/user/images/recover_btn.png
doc_src/user/images/recover_list.png
docs/author_guide.html
docs/genindex.html
docs/index.html
docs/install.html
docs/pagination.html
docs/py-modindex.html
docs/search.html
docs/searchindex.js
docs/settings.html
docs/upgrading.html
docs/_images/history_btn.png
docs/_images/history_list.png
docs/_images/history_save_btn.png
docs/_images/recover_btn.png
docs/_images/recover_list.png
docs/_static/ajax-loader.gif
docs/_static/basic.css
docs/_static/breadcrumb_background.png
docs/_static/comment-bright.png
docs/_static/comment-close.png
docs/_static/comment.png
docs/_static/default.css
docs/_static/doctools.js
docs/_static/documentation.png
docs/_static/down-pressed.png
docs/_static/down.png
docs/_static/file.png
