Metadata-Version: 1.1
Name: django-stories
Version: 1.0.3
Summary: An application for handling newspaper-like stories on a web site
Home-page: http://github.com/callowayproject/django-stories/
Author: Calloway Project
Author-email: webmaster@callowayproject.com
License: UNKNOWN
Platform: UNKNOWN
Classifier: License :: OSI Approved :: Apache Software License
Classifier: Framework :: Django
